tests/exchanges/__init__.py
tests/exchanges/test_ascendex.py
tests/exchanges/test_binance.py
tests/exchanges/test_bitget.py
tests/exchanges/test_bybit.py
tests/exchanges/test_exchange.py
tests/exchanges/test_gateio.py
tests/exchanges/test_huobi.py
tests/exchanges/test_huobipro.py
tests/exchanges/test_okx.py
tests/exchanges/test_phemex.py
tests/util/__init__.py
tests/util/create_order_tests.py
trading_backend/__init__.py
trading_backend/errors.py
trading_backend/exchange_factory.py
trading_backend/exchanges/__init__.py
trading_backend/exchanges/ascendex.py
trading_backend/exchanges/binance.py
trading_backend/exchanges/bitget.py
trading_backend/exchanges/bybit.py
trading_backend/exchanges/exchange.py
trading_backend/exchanges/gateio.py
trading_backend/exchanges/huobi.py
trading_backend/exchanges/huobipro.py
trading_backend/exchanges/okx.py
trading_backend/exchanges/phemex.py
trading_backend-1.0.19.dist-info/LICENSE
trading_backend-1.0.19.dist-info/METADATA
trading_backend-1.0.19.dist-info/WHEEL
trading_backend-1.0.19.dist-info/top_level.txt
trading_backend-1.0.19.dist-info/RECORD
