Metadata-Version: 2.1
Name: trading-backend
Version: 1.0.19
Summary: Trading tools
Home-page: https://github.com/Drakkar-Software/trading-backend
Author: Drakkar-Software
Author-email: drakkar-software@protonmail.com
License: LGPL-3.0
Classifier: Development Status :: 5 - Production/Stable
Classifier: Operating System :: OS Independent
Classifier: Operating System :: MacOS :: MacOS X
Classifier: Operating System :: Microsoft :: Windows
Classifier: Operating System :: POSIX
Classifier: Programming Language :: Python :: 3.8
Classifier: Programming Language :: Python :: 3.9
Requires-Python: >=3.8
License-File: LICENSE
Requires-Dist: setuptools
Requires-Dist: ccxt
